[{"__type__":"cc.SpriteFrame","content":{"name":"eat_white_03","texture":"e2IIwEbdRF84/XFmsKhYVZ","rect":[105,1,22,65],"offset":[0,0],"originalSize":[22,65],"capInsets":[0,0,0,0]}},{"__type__":"cc.SpriteFrame","content":{"name":"eat_white_05","texture":"e2IIwEbdRF84/XFmsKhYVZ","rect":[105,1,22,65],"offset":[0,0],"originalSize":[22,65],"capInsets":[0,0,0,0]}},{"__type__":"cc.AnimationClip","_name":"record_eat","_duration":1.6,"sample":5,"wrapMode":"2","curveData":{"comps":{"cc.Sprite":{"spriteFrame":[{"frame":0,"value":{"__uuid__":"b7SBJ6qD1EsI4olewi6tK8"}},{"frame":0.2,"value":{"__uuid__":"e8Fm97kK1KnbLxp24AMX1n"}},{"frame":0.4,"value":{"__uuid__":"1ftDi/y8NGZIVPiOmnikGf"}},{"frame":0.6,"value":{"__uuid__":"aaZszQAOtLkp+lQh61CHEc"}},{"frame":0.8,"value":{"__uuid__":"21ly/qF6FAwJGjfUeyr7R2"}},{"frame":1,"value":{"__uuid__":"f1Sq3RFCFNBKPDmpIDhBdT"}},{"frame":1.2,"value":{"__uuid__":"ac0TV5PF1GxpteHQ8QRMTl"}},{"frame":1.4,"value":{"__uuid__":"5aoCIrxYNJ7JEa55rCg6SB"}}]}}}},{"__type__":"cc.SpriteFrame","content":{"name":"eat_white_08","texture":"e2IIwEbdRF84/XFmsKhYVZ","rect":[105,68,22,55],"offset":[0,-5],"originalSize":[22,65],"capInsets":[0,0,0,0]}},{"__type__":"cc.SpriteFrame","content":{"name":"eat_white_04","texture":"e2IIwEbdRF84/XFmsKhYVZ","rect":[105,68,22,55],"offset":[0,-5],"originalSize":[22,65],"capInsets":[0,0,0,0]}},{"__type__":"cc.SpriteFrame","content":{"name":"eat_white_07","texture":"e2IIwEbdRF84/XFmsKhYVZ","rect":[105,1,22,65],"offset":[0,0],"originalSize":[22,65],"capInsets":[0,0,0,0]}},{"__type__":"cc.SpriteFrame","content":{"name":"eat_white_01","texture":"e2IIwEbdRF84/XFmsKhYVZ","rect":[105,1,22,65],"offset":[0,0],"originalSize":[22,65],"capInsets":[0,0,0,0]}},{"__type__":"cc.SpriteFrame","content":{"name":"eat_white_02","texture":"e2IIwEbdRF84/XFmsKhYVZ","rect":[105,68,22,55],"offset":[0,-5],"originalSize":[22,65],"capInsets":[0,0,0,0]}},{"__type__":"cc.SpriteFrame","content":{"name":"eat_white_06","texture":"e2IIwEbdRF84/XFmsKhYVZ","rect":[105,68,22,55],"offset":[0,-5],"originalSize":[22,65],"capInsets":[0,0,0,0]}}]